databricks_jobs/__init__.py
databricks_jobs/api_client.py
databricks_jobs/configuration.py
databricks_jobs/exceptions.py
databricks_jobs/py.typed
databricks_jobs/rest.py
databricks_jobs/api/__init__.py
databricks_jobs/api/default_api.py
databricks_jobs/models/__init__.py
databricks_jobs/models/access_control_list.py
databricks_jobs/models/access_control_request.py
databricks_jobs/models/access_control_request_for_group.py
databricks_jobs/models/access_control_request_for_service_principal.py
databricks_jobs/models/access_control_request_for_user.py
databricks_jobs/models/adlsgen2_info.py
databricks_jobs/models/auto_scale.py
databricks_jobs/models/aws_attributes.py
databricks_jobs/models/azure_attributes.py
databricks_jobs/models/can_manage.py
databricks_jobs/models/can_manage_run.py
databricks_jobs/models/can_view.py
databricks_jobs/models/cluster_attributes.py
databricks_jobs/models/cluster_cloud_provider_node_info.py
databricks_jobs/models/cluster_cloud_provider_node_status.py
databricks_jobs/models/cluster_event.py
databricks_jobs/models/cluster_event_type.py
databricks_jobs/models/cluster_info.py
databricks_jobs/models/cluster_instance.py
databricks_jobs/models/cluster_library_statuses.py
databricks_jobs/models/cluster_log_conf.py
databricks_jobs/models/cluster_size.py
databricks_jobs/models/cluster_source.py
databricks_jobs/models/cluster_spec.py
databricks_jobs/models/cluster_state.py
databricks_jobs/models/cron_schedule.py
databricks_jobs/models/dbfs_storage_info.py
databricks_jobs/models/dbt_output.py
databricks_jobs/models/dbt_task.py
databricks_jobs/models/docker_basic_auth.py
databricks_jobs/models/docker_image.py
databricks_jobs/models/error.py
databricks_jobs/models/event_details.py
databricks_jobs/models/file_storage_info.py
databricks_jobs/models/gcp_attributes.py
databricks_jobs/models/git_branch_source.py
databricks_jobs/models/git_commit_source.py
databricks_jobs/models/git_provider.py
databricks_jobs/models/git_snapshot.py
databricks_jobs-1.0.3.dist-info/METADATA
databricks_jobs-1.0.3.dist-info/WHEEL
databricks_jobs-1.0.3.dist-info/top_level.txt
databricks_jobs-1.0.3.dist-info/RECORD
