Metadata-Version: 2.1
Name: databricks-jobs
Version: 1.0.3
Summary: Databricks Jobs API 2.1 Client
Home-page: https://github.com/judahrand/databricks-jobs
Author: Judah Rand
Author-email: 17158624+judahrand@users.noreply.github.com
Keywords: OpenAPI,OpenAPI-Generator,Databricks,Jobs API 2.1
Requires-Python: >=3.8
Requires-Dist: urllib3 (>=1.25.3)
Requires-Dist: python-dateutil
Requires-Dist: pydantic
Requires-Dist: aenum
